setup.py
scouter/__init__.py
scouter/sbase.py
scouter/sdict.py
scouter/slist.py
scouter/svar.py
scouter.egg-info/PKG-INFO
scouter.egg-info/SOURCES.txt
scouter.egg-info/dependency_links.txt
scouter.egg-info/not-zip-safe
scouter.egg-info/top_level.txt
scouter/sop/__init__.py
scouter/sop/fsm.py