Metadata-Version: 1.0
Name: scouter
Version: 0.1.3
Summary: Watching Data with Callback!
Home-page: https://github.com/VillanCh/scouter
Author: v1ll4n
Author-email: v1ll4n@villanch.top
License: BSD 2-Clause License
Platform: UNKNOWN
